jira_tool/__init__.py
jira_tool/__main__.py
jira_tool/main_test.py
jira_tool/test.py
jira_tool-0.0.2.dist-info/METADATA
jira_tool-0.0.2.dist-info/WHEEL
jira_tool-0.0.2.dist-info/entry_points.txt
jira_tool-0.0.2.dist-info/top_level.txt
jira_tool-0.0.2.dist-info/RECORD
