Metadata-Version: 2.1
Name: jira-tool
Version: 0.0.2
Summary: create jira issue from markdown file
Home-page: https://github.com/LogosFu/jira_tool_create
Author: LogosFu
Author-email: logosfu@gmail.com
License: GNU General Public License v3.0
Platform: UNKNOWN
Requires-Python: >=3.6
Requires-Dist: setuptools (~=57.1.0)
Requires-Dist: mistletoe (~=0.7.2)
Requires-Dist: requests (~=2.25.1)
